diem/__VERSION__.py
diem/__init__.py
diem/auth_key.py
diem/chain_ids.py
diem/constants.py
diem/jws.py
diem/testnet.py
diem/txnmetadata.py
diem/utils.py
diem/bcs/__init__.py
diem/diem_types/__init__.py
diem/identifier/__init__.py
diem/identifier/bech32.py
diem/identifier/diem_id.py
diem/identifier/subaddress.py
diem/jsonrpc/__init__.py
diem/jsonrpc/async_client.py
diem/jsonrpc/client.py
diem/jsonrpc/constants.py
diem/jsonrpc/errors.py
diem/jsonrpc/jsonrpc_pb2.py
diem/jsonrpc/state.py
diem/offchain/__init__.py
diem/offchain/action.py
diem/offchain/client.py
diem/offchain/command.py
diem/offchain/error.py
diem/offchain/http_header.py
diem/offchain/http_server.py
diem/offchain/jws.py
diem/offchain/payment_command.py
diem/offchain/payment_state.py
diem/offchain/reference_id_command.py
diem/offchain/state.py
diem/offchain/types/__init__.py
diem/offchain/types/command_types.py
diem/offchain/types/payment_types.py
diem/serde_binary/__init__.py
diem/serde_types/__init__.py
diem/stdlib/__init__.py
diem/testing/__init__.py
diem/testing/cli.py
diem/testing/constants.py
diem/testing/faucet.py
diem/testing/local_account.py
diem/testing/miniwallet/__init__.py
diem/testing/miniwallet/client.py
diem/testing/miniwallet/config.py
diem/testing/miniwallet/app/__init__.py
diem/testing/miniwallet/app/api.py
diem/testing/miniwallet/app/app.py
diem/testing/miniwallet/app/diem_account.py
diem/testing/miniwallet/app/event_puller.py
diem/testing/miniwallet/app/json_input.py
diem/testing/miniwallet/app/models.py
diem/testing/miniwallet/app/offchain_api_v2.py
diem/testing/miniwallet/app/pending_account.py
diem/testing/miniwallet/app/store.py
diem/testing/miniwallet/app/static/index.html
diem/testing/miniwallet/app/static/openapi.yaml
diem/testing/suites/__init__.py
diem/testing/suites/conftest.py
diem/testing/suites/envs.py
diem/testing/suites/basic/__init__.py
diem/testing/suites/basic/test_create_test_account.py
diem/testing/suites/basic/test_diem_id.py
diem-1.7.1.dist-info/LICENSE
diem-1.7.1.dist-info/METADATA
diem-1.7.1.dist-info/WHEEL
diem-1.7.1.dist-info/entry_points.txt
diem-1.7.1.dist-info/top_level.txt
diem-1.7.1.dist-info/zip-safe
diem-1.7.1.dist-info/RECORD
