Metadata-Version: 2.1
Name: diem
Version: 1.7.1
Summary: The Python Client SDK for Diem
Home-page: https://github.com/diem/client-sdk-python
Author: The Diem Core Contributors
Author-email: developers@diem.com
License: Apache-2.0
Platform: UNKNOWN
Classifier: Programming Language :: Python :: 3.7
Classifier: Programming Language :: Python :: 3.8
Classifier: Programming Language :: Python :: 3.9
Requires-Python: >=3.7
License-File: LICENSE
Requires-Dist: requests (>=2.20.0)
Requires-Dist: cryptography (>=2.8)
Requires-Dist: numpy (>=1.18)
Requires-Dist: protobuf (>=3.12.4)
Requires-Dist: aiohttp (>=3.7.3)
Provides-Extra: all
Requires-Dist: falcon (>=2.0.0) ; extra == 'all'
Requires-Dist: waitress (>=1.4.4) ; extra == 'all'
Requires-Dist: pytest (>=6.2.1) ; extra == 'all'
Requires-Dist: click (>=7.1) ; extra == 'all'
